aquery/Iquery.py
aquery/__init__.py
aquery/database.py
aquery/query.py
aquery/query_model.py
aquery/version.py
aquery/handler/__init__.py
aquery/handler/abs_handler.py
aquery/handler/cursor_handler.py
aquery/handler/param_handler.py
aquery/handler/sql_handler.py
aquery/util/__init__.py
aquery/util/errors.py
aquery/util/logger.py
aquery/util/sql_util.py
AQuery-0.0.3.dist-info/METADATA
AQuery-0.0.3.dist-info/WHEEL
AQuery-0.0.3.dist-info/top_level.txt
AQuery-0.0.3.dist-info/zip-safe
AQuery-0.0.3.dist-info/RECORD
