Metadata-Version: 2.1
Name: AQuery
Version: 0.0.3
Summary: 一个MySQL注解操作方式
Home-page: https://github.com/mouday/AQuery
Author: Peng Shiyu
Author-email: pengshiyuyx@gmail.com
License: MIT
Keywords: aquery mysql
Platform: UNKNOWN
Classifier: Programming Language :: Python :: 3.7
Requires-Dist: mysql-connector-python (==8.0.17)
